cleaner/__init__.py
scrape_data_cleaner-0.0.26.dist-info/LICENSE
scrape_data_cleaner-0.0.26.dist-info/METADATA
scrape_data_cleaner-0.0.26.dist-info/WHEEL
scrape_data_cleaner-0.0.26.dist-info/top_level.txt
scrape_data_cleaner-0.0.26.dist-info/RECORD
