Metadata-Version: 2.1
Name: scrape-data-cleaner
Version: 0.0.26
Summary: A package for cleaning forms of scraped data and convert them to normal text.
Home-page: 
Author: Alexander Njogu
Author-email: Alexander@chekiprice.com
Project-URL: Bug Tracker, https://gitlab.com:xaander1/scraped-data-cleaner.git
Classifier: Programming Language :: Python :: 3
Classifier: License :: OSI Approved :: MIT License
Classifier: Operating System :: OS Independent
Requires-Python: >=3.6
License-File: LICENSE
